observex/__init__.py
observex/observex.py
observex/core/__init__.py
observex/core/base.py
observex/core/exceptions.py
observex/core/utils.py
observex/executors/__init__.py
observex/executors/oxexecutors.py
observex/integrations/__init__.py
observex/integrations/databricksintegration.py
observex/integrations/msfabricintegration.py
observex/observers/__init__.py
observex/observers/columnobservers.py
observex/observers/datasetobservers.py
observex/observers/metadataobservers.py
observex/observers/observerbase.py
observex/observers/rowobservers.py
observex-0.0.50924.dist-info/METADATA
observex-0.0.50924.dist-info/WHEEL
observex-0.0.50924.dist-info/top_level.txt
observex-0.0.50924.dist-info/RECORD
