Metadata-Version: 2.1
Name: observex
Version: 0.0.50924
Summary: BiSense library for BI comparisons
Author: Ilink-Data
Author-email: Arnayj@ilink-systems.com
Requires-Python: >=3.7
